{"container_type": "Author", "filled": ["basics", "publications", "indices", "counts"], "scholar_id": "CMiRzlAAAAAJ", "source": "AUTHOR_PROFILE_PAGE", "name": "Qingsong Yao", "url_picture": "https://scholar.googleusercontent.com/citations?view_op=view_photo&user=CMiRzlAAAAAJ&citpid=7", "affiliation": "Stanford University | ICT, CAS", "organization": 8539678734835078480, "interests": ["Medical Image Computing", "Medical Image Analysis"], "email_domain": "@stanford.edu", "homepage": "https://qsyao.github.io/", "citedby": 553, "publications": {"CMiRzlAAAAAJ:d1gkVwhDpl0C": {"container_type": "Publication", "source": "AUTHOR_PUBLICATION_ENTRY", "bib": {"title": "Label-free segmentation of COVID-19 lesions in lung CT", "pub_year": "2021"}, "filled": false, "author_pub_id": "CMiRzlAAAAAJ:d1gkVwhDpl0C", "num_citations": 148, "citedby_url": "https://scholar.google.com/scholar?oi=bibs&hl=en&cites=9242756268331685424", "cites_id": ["9242756268331685424"]}, "CMiRzlAAAAAJ:u5HHmVD_uO8C": {"container_type": "Publication", "source": "AUTHOR_PUBLICATION_ENTRY", "bib": {"title": "3D U 2-Net: A 3D universal U-Net for multi-domain medical image segmentation", "pub_year": "2019"}, "filled": false, "author_pub_id": "CMiRzlAAAAAJ:u5HHmVD_uO8C", "num_citations": 129, "citedby_url": "https://scholar.google.com/scholar?oi=bibs&hl=en&cites=3979204286359317621", "cites_id": ["3979204286359317621"]}, "CMiRzlAAAAAJ:YOwf2qJgpHMC": {"container_type": "Publication", "source": "AUTHOR_PUBLICATION_ENTRY", "bib": {"title": "You only learn once: Universal anatomical landmark detection", "pub_year": "2021"}, "filled": false, "author_pub_id": "CMiRzlAAAAAJ:YOwf2qJgpHMC", "num_citations": 67, "citedby_url": "https://scholar.google.com/scholar?oi=bibs&hl=en&cites=11019093677845069928,3496396485834196026", "cites_id": ["11019093677845069928", "3496396485834196026"]}, "CMiRzlAAAAAJ:u-x6o8ySG0sC": {"container_type": "Publication", "source": "AUTHOR_PUBLICATION_ENTRY", "bib": {"title": "Miss the point: Targeted adversarial attack on multiple landmark detection", "pub_year": "2020"}, "filled": false, "author_pub_id": "CMiRzlAAAAAJ:u-x6o8ySG0sC", "num_citations": 43, "citedby_url": "https://scholar.google.com/scholar?oi=bibs&hl=en&cites=8426202239570789776", "cites_id": ["8426202239570789776"]}, "CMiRzlAAAAAJ:qjMakFHDy7sC": {"container_type": "Publication", "source": "AUTHOR_PUBLICATION_ENTRY", "bib": {"title": "One-Shot Medical Landmark Detection", "pub_year": "2021"}, "filled": false, "author_pub_id": "CMiRzlAAAAAJ:qjMakFHDy7sC", "num_citations": 37, "citedby_url": "https://scholar.google.com/scholar?oi=bibs&hl=en&cites=6882645392250727102", "cites_id": ["6882645392250727102"]}, "CMiRzlAAAAAJ:QIV2ME_5wuYC": {"container_type": "Publication", "source": "AUTHOR_PUBLICATION_ENTRY", "bib": {"title": "Which images to label for few-shot medical image analysis?", "pub_year": "2024"}, "filled": false, "author_pub_id": "CMiRzlAAAAAJ:QIV2ME_5wuYC", "num_citations": 26, "citedby_url": "https://scholar.google.com/scholar?oi=bibs&hl=en&cites=14199234960983706988,9794584455244136151", "cites_id": ["14199234960983706988", "9794584455244136151"]}, "CMiRzlAAAAAJ:3fE2CSJIrl8C": {"container_type": "Publication", "source": "AUTHOR_PUBLICATION_ENTRY", "bib": {"title": "Adversarial Medical Image with Hierarchical Feature Hiding", "pub_year": "2023"}, "filled": false, "author_pub_id": "CMiRzlAAAAAJ:3fE2CSJIrl8C", "num_citations": 24, "citedby_url": "https://scholar.google.com/scholar?oi=bibs&hl=en&cites=8115651155693161777,6684174236956986367", "cites_id": ["8115651155693161777", "6684174236956986367"]}, "CMiRzlAAAAAJ:-f6ydRqryjwC": {"container_type": "Publication", "source": "AUTHOR_PUBLICATION_ENTRY", "bib": {"title": "Addressing fairness issues in deep learning-based medical image analysis: a systematic review", "pub_year": "2024"}, "filled": false, "author_pub_id": "CMiRzlAAAAAJ:-f6ydRqryjwC", "num_citations": 16, "citedby_url": "https://scholar.google.com/scholar?oi=bibs&hl=en&cites=6249427827550340171,9546987996302808844,7505285013856235413,1668692926836609795", "cites_id": ["6249427827550340171", "9546987996302808844", "7505285013856235413", "1668692926836609795"]}, "CMiRzlAAAAAJ:_FxGoFyzp5QC": {"container_type": "Publication", "source": "AUTHOR_PUBLICATION_ENTRY", "bib": {"title": "Datr: Domain-adaptive transformer for multi-domain landmark detection", "pub_year": "2022"}, "filled": false, "author_pub_id": "CMiRzlAAAAAJ:_FxGoFyzp5QC", "num_citations": 14, "citedby_url": "https://scholar.google.com/scholar?oi=bibs&hl=en&cites=1569386427391229051", "cites_id": ["1569386427391229051"]}, "CMiRzlAAAAAJ:UebtZRa9Y70C": {"container_type": "Publication", "source": "AUTHOR_PUBLICATION_ENTRY", "bib": {"title": "FairAdaBN: Mitigating unfairness with adaptive batch normalization and its application to dermatological disease classification", "pub_year": "2023"}, "filled": false, "author_pub_id": "CMiRzlAAAAAJ:UebtZRa9Y70C", "num_citations": 9, "citedby_url": "https://scholar.google.com/scholar?oi=bibs&hl=en&cites=13259552445624356587", "cites_id": ["13259552445624356587"]}, "CMiRzlAAAAAJ:ZeXyd9-uunAC": {"container_type": "Publication", "source": "AUTHOR_PUBLICATION_ENTRY", "bib": {"title": "IGU-Aug: Information-guided unsupervised augmentation and pixel-wise contrastive learning for medical image analysis", "pub_year": "2024"}, "filled": false, "author_pub_id": "CMiRzlAAAAAJ:ZeXyd9-uunAC", "num_citations": 8, "citedby_url": "https://scholar.google.com/scholar?oi=bibs&hl=en&cites=5340615564496882825,7507016364846025569,2276990851818085623", "cites_id": ["5340615564496882825", "7507016364846025569", "2276990851818085623"]}, "CMiRzlAAAAAJ:0EnyYjriUFMC": {"container_type": "Publication", "source": "AUTHOR_PUBLICATION_ENTRY", "bib": {"title": "Uod: Universal one-shot detection of anatomical landmarks", "pub_year": "2023"}, "filled": false, "author_pub_id": "CMiRzlAAAAAJ:0EnyYjriUFMC", "num_citations": 8, "citedby_url": "https://scholar.google.com/scholar?oi=bibs&hl=en&cites=10107969706819082009", "cites_id": ["10107969706819082009"]}, "CMiRzlAAAAAJ:qxL8FJ1GzNcC": {"container_type": "Publication", "source": "AUTHOR_PUBLICATION_ENTRY", "bib": {"title": "CARZero: Cross-Attention Alignment for Radiology Zero-Shot Classification", "pub_year": "2024"}, "filled": false, "author_pub_id": "CMiRzlAAAAAJ:qxL8FJ1GzNcC", "num_citations": 5, "citedby_url": "https://scholar.google.com/scholar?oi=bibs&hl=en&cites=2540710193175339092", "cites_id": ["2540710193175339092"]}, "CMiRzlAAAAAJ:qUcmZB5y_30C": {"container_type": "Publication", "source": "AUTHOR_PUBLICATION_ENTRY", "bib": {"title": "Nowhere to Hide: Toward Robust Reactive Medical Adversarial Defense", "pub_year": "2024"}, "filled": false, "author_pub_id": "CMiRzlAAAAAJ:qUcmZB5y_30C", "num_citations": 4, "citedby_url": "https://scholar.google.com/scholar?oi=bibs&hl=en&cites=12660837157925265347,6532932452560088812", "cites_id": ["12660837157925265347", "6532932452560088812"]}, "CMiRzlAAAAAJ:ULOm3_A8WrAC": {"container_type": "Publication", "source": "AUTHOR_PUBLICATION_ENTRY", "bib": {"title": "ECAMP: Entity-centered Context-aware Medical Vision Language Pre-training", "pub_year": "2023"}, "filled": false, "author_pub_id": "CMiRzlAAAAAJ:ULOm3_A8WrAC", "num_citations": 4, "citedby_url": "https://scholar.google.com/scholar?oi=bibs&hl=en&cites=15574042176316891372", "cites_id": ["15574042176316891372"]}, "CMiRzlAAAAAJ:9ZlFYXVOiuMC": {"container_type": "Publication", "source": "AUTHOR_PUBLICATION_ENTRY", "bib": {"title": "Relative distance matters for one-shot landmark detection", "pub_year": "2022"}, "filled": false, "author_pub_id": "CMiRzlAAAAAJ:9ZlFYXVOiuMC", "num_citations": 4, "citedby_url": "https://scholar.google.com/scholar?oi=bibs&hl=en&cites=7318773206463749119", "cites_id": ["7318773206463749119"]}, "CMiRzlAAAAAJ:ufrVoPGSRksC": {"container_type": "Publication", "source": "AUTHOR_PUBLICATION_ENTRY", "bib": {"title": "Rib Suppression in Digital Chest Tomosynthesis", "pub_year": "2022"}, "filled": false, "author_pub_id": "CMiRzlAAAAAJ:ufrVoPGSRksC", "num_citations": 3, "citedby_url": "https://scholar.google.com/scholar?oi=bibs&hl=en&cites=1143584338293347036", "cites_id": ["1143584338293347036"]}, "CMiRzlAAAAAJ:L8Ckcad2t8MC": {"container_type": "Publication", "source": "AUTHOR_PUBLICATION_ENTRY", "bib": {"title": "FairMedFM: Fairness Benchmarking for Medical Imaging Foundation Models", "pub_year": "2024"}, "filled": false, "author_pub_id": "CMiRzlAAAAAJ:L8Ckcad2t8MC", "num_citations": 2, "citedby_url": "https://scholar.google.com/scholar?oi=bibs&hl=en&cites=18123470773123772487", "cites_id": ["18123470773123772487"]}, "CMiRzlAAAAAJ:IWHjjKOFINEC": {"container_type": "Publication", "source": "AUTHOR_PUBLICATION_ENTRY", "bib": {"title": "HySparK: Hybrid Sparse Masking for Large Scale Medical Image Pre-Training", "pub_year": "2024"}, "filled": false, "author_pub_id": "CMiRzlAAAAAJ:IWHjjKOFINEC", "num_citations": 1, "citedby_url": "https://scholar.google.com/scholar?oi=bibs&hl=en&cites=17230071921831874321", "cites_id": ["17230071921831874321"]}, "CMiRzlAAAAAJ:Wp0gIr-vW9MC": {"container_type": "Publication", "source": "AUTHOR_PUBLICATION_ENTRY", "bib": {"title": "APPLE: Adversarial Privacy-aware Perturbations on Latent Embedding for Unfairness Mitigation", "pub_year": "2024"}, "filled": false, "author_pub_id": "CMiRzlAAAAAJ:Wp0gIr-vW9MC", "num_citations": 1, "citedby_url": "https://scholar.google.com/scholar?oi=bibs&hl=en&cites=14904923539240956123", "cites_id": ["14904923539240956123"]}, "CMiRzlAAAAAJ:mB3voiENLucC": {"container_type": "Publication", "source": "AUTHOR_PUBLICATION_ENTRY", "bib": {"title": "Hybrid Attention Network: An efficient approach for anatomy-free landmark detection", "pub_year": "2024"}, "filled": false, "author_pub_id": "CMiRzlAAAAAJ:mB3voiENLucC", "num_citations": 0}, "CMiRzlAAAAAJ:hFOr9nPyWt4C": {"container_type": "Publication", "source": "AUTHOR_PUBLICATION_ENTRY", "bib": {"title": "E3D-GPT: Enhanced 3D Visual Foundation for Medical Vision-Language Model", "pub_year": "2024"}, "filled": false, "author_pub_id": "CMiRzlAAAAAJ:hFOr9nPyWt4C", "num_citations": 0}, "CMiRzlAAAAAJ:hC7cP41nSMkC": {"container_type": "Publication", "source": "AUTHOR_PUBLICATION_ENTRY", "bib": {"title": "SIX-Net: Spatial-Context Information miX-up for Electrode Landmark Detection", "pub_year": "2024"}, "filled": false, "author_pub_id": "CMiRzlAAAAAJ:hC7cP41nSMkC", "num_citations": 0}, "CMiRzlAAAAAJ:MXK_kJrjxJIC": {"container_type": "Publication", "source": "AUTHOR_PUBLICATION_ENTRY", "bib": {"title": "Long-tailed multi-label classification with noisy label of thoracic diseases from chest X-ray", "pub_year": "2023"}, "filled": false, "author_pub_id": "CMiRzlAAAAAJ:MXK_kJrjxJIC", "num_citations": 0}}, "citedby5y": 552, "hindex": 9, "hindex5y": 9, "i10index": 9, "i10index5y": 9, "cites_per_year": {"2020": 20, "2021": 87, "2022": 108, "2023": 135, "2024": 192}, "updated": "2024-12-24 08:27:05.835937"}